masquerade/__init__.py
masquerade/cli.py
masquerade/masquerade.py
masquerade_spatial-0.1.2.dist-info/METADATA
masquerade_spatial-0.1.2.dist-info/WHEEL
masquerade_spatial-0.1.2.dist-info/entry_points.txt
masquerade_spatial-0.1.2.dist-info/top_level.txt
masquerade_spatial-0.1.2.dist-info/RECORD
