Metadata-Version: 2.4
Name: masquerade-spatial
Version: 0.1.2
Summary: Spatial image analysis and mask generation for microscopy data
Author-email: Eduardo Esteva <Eduardo.Esteva@nyulangone.org>
License: MIT
Project-URL: Homepage, https://github.com/e-esteva/masquerade
Project-URL: Documentation, https://masquerade.readthedocs.io/
Project-URL: Repository, https://github.com/e-esteva/masquerade.git
Project-URL: Bug Tracker, https://github.com/e-esteva/masquerade/issues
Keywords: spatial-biology,microscopy,image-processing,masks,tiff,biomarkers,clustering
Classifier: Development Status :: 3 - Alpha
Classifier: Intended Audience :: Science/Research
Classifier: License :: OSI Approved :: MIT License
Classifier: Operating System :: OS Independent
Classifier: Programming Language :: Python :: 3
Classifier: Programming Language :: Python :: 3.8
Classifier: Programming Language :: Python :: 3.9
Classifier: Programming Language :: Python :: 3.10
Classifier: Programming Language :: Python :: 3.11
Classifier: Topic :: Scientific/Engineering :: Image Processing
Classifier: Topic :: Scientific/Engineering :: Bio-Informatics
Requires-Python: >=3.8
Requires-Dist: imagecodecs>=2021.11.20
Requires-Dist: scikit-image>=0.19.0
Requires-Dist: pandas>=1.3.0
Requires-Dist: numpy>=1.20.0
Requires-Dist: matplotlib>=3.5.0
Requires-Dist: tifffile>=2021.11.2
Requires-Dist: scipy>=1.7.0
Requires-Dist: tqdm>=4.60.0
Provides-Extra: dev
Requires-Dist: pytest>=6.0; extra == "dev"
Requires-Dist: pytest-cov>=2.0; extra == "dev"
Requires-Dist: black>=21.0; extra == "dev"
Requires-Dist: flake8>=3.8; extra == "dev"
Requires-Dist: isort>=5.0; extra == "dev"
Requires-Dist: mypy>=0.910; extra == "dev"
Provides-Extra: docs
Requires-Dist: sphinx>=4.0; extra == "docs"
Requires-Dist: sphinx-rtd-theme>=1.0; extra == "docs"
